hypercorn/__about__.py
hypercorn/__init__.py
hypercorn/__main__.py
hypercorn/config.py
hypercorn/events.py
hypercorn/logging.py
hypercorn/py.typed
hypercorn/run.py
hypercorn/statsd.py
hypercorn/typing.py
hypercorn/utils.py
hypercorn/asyncio/__init__.py
hypercorn/asyncio/context.py
hypercorn/asyncio/lifespan.py
hypercorn/asyncio/run.py
hypercorn/asyncio/statsd.py
hypercorn/asyncio/task_group.py
hypercorn/asyncio/tcp_server.py
hypercorn/asyncio/udp_server.py
hypercorn/middleware/__init__.py
hypercorn/middleware/dispatcher.py
hypercorn/middleware/http_to_https.py
hypercorn/middleware/wsgi.py
hypercorn/protocol/__init__.py
hypercorn/protocol/events.py
hypercorn/protocol/h11.py
hypercorn/protocol/h2.py
hypercorn/protocol/h3.py
hypercorn/protocol/http_stream.py
hypercorn/protocol/quic.py
hypercorn/protocol/ws_stream.py
hypercorn/trio/__init__.py
hypercorn/trio/context.py
hypercorn/trio/lifespan.py
hypercorn/trio/run.py
hypercorn/trio/statsd.py
hypercorn/trio/tcp_server.py
hypercorn/trio/udp_server.py
Hypercorn_noteable-0.11.3.dist-info/LICENSE
Hypercorn_noteable-0.11.3.dist-info/METADATA
Hypercorn_noteable-0.11.3.dist-info/WHEEL
Hypercorn_noteable-0.11.3.dist-info/entry_points.txt
Hypercorn_noteable-0.11.3.dist-info/top_level.txt
Hypercorn_noteable-0.11.3.dist-info/RECORD
