Metadata-Version: 2.1
Name: Hypercorn-noteable
Version: 0.11.3
Summary: A ASGI Server based on Hyper libraries and inspired by Gunicorn.
Home-page: https://github.com/noteable-io/hypercorn/
Author: Noteable (extending from P G Jones)
Author-email: engineering@noteable.io
License: MIT
Platform: UNKNOWN
Classifier: Development Status :: 4 - Beta
Classifier: Environment :: Web Environment
Classifier: Intended Audience :: Developers
Classifier: License :: OSI Approved :: MIT License
Classifier: Operating System :: OS Independent
Classifier: Programming Language :: Python
Classifier: Programming Language :: Python :: 3
Classifier: Programming Language :: Python :: 3.7
Classifier: Programming Language :: Python :: 3.8
Classifier: Programming Language :: Python :: 3.9
Classifier: Topic :: Internet :: WWW/HTTP :: Dynamic Content
Classifier: Topic :: Software Development :: Libraries :: Python Modules
Requires-Python: >=3.7
Requires-Dist: h11
Requires-Dist: h2 (>=3.1.0)
Requires-Dist: priority
Requires-Dist: toml
Requires-Dist: wsproto (>=0.14.0)
Requires-Dist: typing-extensions ; python_version < "3.8"
Provides-Extra: h3
Requires-Dist: aioquic (<1.0,>=0.9.0) ; extra == 'h3'
Provides-Extra: tests
Requires-Dist: hypothesis ; extra == 'tests'
Requires-Dist: mock ; extra == 'tests'
Requires-Dist: pytest ; extra == 'tests'
Requires-Dist: pytest-asyncio ; extra == 'tests'
Requires-Dist: pytest-cov ; extra == 'tests'
Requires-Dist: pytest-trio ; extra == 'tests'
Requires-Dist: trio ; extra == 'tests'
Provides-Extra: trio
Requires-Dist: trio (>=0.11.0) ; extra == 'trio'
Provides-Extra: uvloop
Requires-Dist: uvloop ; extra == 'uvloop'
